{
 "id": "56990691",
 "blocks": [
  {
   "upper_left_point": {
    "x": 105,
    "y": 112
   },
   "bottom_right_point": {
    "x": 432,
    "y": 266
   },
   "text": "שוידער האָט אונדז אַרומגעכאפט ביים דורכגיין שטעט און שטעטלעך פון פוילן ווו עס האָט געברויזט מיט יידיש לעבן גאַנצע יאָרהונדערטער , און מיר האָבן זיי געזען אויסגעליידיקט פון יידן . די אלטע יידישע קהילות זענען אַרויסגעריסן און פאַרניכטעט געוואָרן , און מיר האָבן זיך איבערצייגט אז עס איז געקומען דער סוף פון דעם פרעכטיקן פוילישן יידנטום . מיר האָבן ניט געוואלט מער פארבלייבן אין פוילן , דאָס לאַנד וואס איז אָנגעזאַפט מיטן בלוט פון מיליאָנען יידן , און מיר האָבן פארגעזעצט אונדזער רייזע קיין מערב , מיטן ציל זיך אָנצושליסן אין די יידישע פליטים מחנות , וואָס האָבן געווארט אויף דער מעגלעכקייט פון עליה קיין ארץ ישראל - דאָס אלטיני יידיש פאָטערלאַנד . ",
   "origin_language": "",
   "target_language": "",
   "translated_text": "Shock gripped us as we passed through the cities and towns of Poland where it was buzzing with Jewish life for centuries, and we saw them emptied of Jews. The old Jewish churches were torn out and destroyed, and we were convinced that the end of the glorious Polish Jewry had come. We no longer wanted to stay in Poland, the country soaked in the blood of millions of Jews, and we continued our journey to the West, with the aim of joining the Jewish refugee camps, which were waiting for the possibility of immigrating to the Land of Israel. - The Altini Jewish homeland. .\n"
  }
 ],
 "filename": "tmp/horodlo/56990691.jpg",
 "order": 127,
 "page_number": "125"
}