{
 "id": "56990611",
 "blocks": [
  {
   "upper_left_point": {
    "x": 348,
    "y": 109
   },
   "bottom_right_point": {
    "x": 431,
    "y": 121
   },
   "text": "הרב חיים בערמאן ",
   "origin_language": "",
   "target_language": "",
   "translated_text": "Rabbi Chaim Barman.\n"
  },
  {
   "upper_left_point": {
    "x": 156,
    "y": 129
   },
   "bottom_right_point": {
    "x": 384,
    "y": 158
   },
   "text": "דער מרא דאתרא , דער האראדלער רב , זצל ( זיין לעבנס־געשיכטע און זיין משפחה ) ",
   "origin_language": "",
   "target_language": "",
   "translated_text": "The Mera Datra, the Haradler Rabbi, Ztzel (his life story and his family).\n"
  },
  {
   "upper_left_point": {
    "x": 108,
    "y": 168
   },
   "bottom_right_point": {
    "x": 433,
    "y": 226
   },
   "text": "צוזאַמען מיט דער הייליקער האָראָדלער קהילה איז אויך אומגעקומען אויף קידוש השם דער מרא דאתרא - מיין פאטער , מורי הרב הגאון , קדוש ה ' . מוהרר משה יהודה לייב הלוי בערמאן היד זצללהה . אויף קידוש השם זענען אויך אומגעקומען דאָס רוב פון זיינע קינדער און אייניקלעך . ",
   "origin_language": "",
   "target_language": "",
   "translated_text": "Along with the Holy Horodlar community, the Mera Datra - my father, teacher Rabbi HaGaon, Holy One, also died on Kiddush Hashem. Muharr Moshe Yehuda Leib Halevi Berman Hid Ztallah. Most of his children and grandchildren also died on Kiddush Hashem. .\n"
  },
  {
   "upper_left_point": {
    "x": 187,
    "y": 600
   },
   "bottom_right_point": {
    "x": 350,
    "y": 624
   },
   "text": "המרא דאתרא הרב דהאראדלה זצל הייד און זיין זון הרב חיים יבלחט ",
   "origin_language": "",
   "target_language": "",
   "translated_text": "The Mera Datra Rabbi Deharadla Zetzel Hyde and Zein Zon Rabbi Chaim Yavlhat.\n"
  }
 ],
 "filename": "tmp/horodlo/56990611.jpg",
 "order": 47,
 "page_number": "45"
}