{
 "id": "56990876",
 "blocks": [
  {
   "upper_left_point": {
    "x": 221,
    "y": 132
   },
   "bottom_right_point": {
    "x": 421,
    "y": 168
   },
   "text": "וויינטרויב דוד , זיין פרוי רבקה און צוויי קינדער . וואגשאל אברהם ( דער זון פון משה ) . ווארמאן ישראל , זיין פרוי און א קינד . ",
   "origin_language": "",
   "target_language": "",
   "translated_text": "Weintroib David, his wife Rebecca and two children. Wagshal Avraham (the son of Moses). Warman Israel, his wife and a child. .\n"
  },
  {
   "upper_left_point": {
    "x": 114,
    "y": 173
   },
   "bottom_right_point": {
    "x": 422,
    "y": 225
   },
   "text": "ווארמאן פינטשע און זיין פרוי . וויינרויב שמואל , זיין פרוי פייגע און דריי קינדער . וויינטרויב חיים מאיר , זיין פרוי לאה , די קינדער : ביילע , זלאטע , ראובן רחל , יצחק . שרה ",
   "origin_language": "",
   "target_language": "",
   "translated_text": "Warman Finche and his wife. Weinroib Shmuel, his wife Fige and three children. Weintroib Chaim Meir, his wife Leah, the children: Bayle, Zlote, Reuven Rachel, Isaac. Sarah.\n"
  },
  {
   "upper_left_point": {
    "x": 288,
    "y": 228
   },
   "bottom_right_point": {
    "x": 423,
    "y": 284
   },
   "text": "װיינטרויב שמואל וויינטרויב משה , זיין פרוי חנה . וינרוט צבי און זיין פאמיליע ווינרוש מלכה ",
   "origin_language": "",
   "target_language": "",
   "translated_text": "Weintraub Shmuel and Moshe Weintraub, Zein Frau Hana. Winrot Zvi and Zane Family Winrosch Malka.\n"
  },
  {
   "upper_left_point": {
    "x": 208,
    "y": 287
   },
   "bottom_right_point": {
    "x": 423,
    "y": 311
   },
   "text": "וויינטרויב דוד , זיין פרוי רבקה . ווינרזש אברהם , זיין פרוי לאה און דריי קינדער . ",
   "origin_language": "",
   "target_language": "",
   "translated_text": "Grape David, his wife Rebecca. Vinrj Avraham, his wife Leah and three children. .\n"
  },
  {
   "upper_left_point": {
    "x": 217,
    "y": 314
   },
   "bottom_right_point": {
    "x": 423,
    "y": 386
   },
   "text": "וויינטרויב שמואל , זיין פרוי חנה . וואלאך משה מענדל און זיין פרוי חיה שיינדל . וואלאך רחל און איר מאן און דריי קינדער . וואלאך אסתר און איר מאן און צוויי קינדער . וואלאך מלכה און איר מאן . ",
   "origin_language": "",
   "target_language": "",
   "translated_text": "Grape Shmuel, his wife Hannah. Wallach Moshe Mendel and his wife Haya Sheindel. Wallach Rachel and her husband and three children. Wallach Esther and her husband and two children. Valach Malka and her husband. .\n"
  },
  {
   "upper_left_point": {
    "x": 154,
    "y": 427
   },
   "bottom_right_point": {
    "x": 423,
    "y": 495
   },
   "text": "זובערמאן יואל יצחק , זיין פרוי חנה . זובערמאן יעקב , זיין פרוי שרה , זייער זון יצחק . זובערמאן משה , זיין פרוי יוכבד , די קינדער : אהרן , רבקה , חיה . זובערמאן שמואל און זיין זון חיים מוני . זובערמאן ביילע , איר זון משה . ",
   "origin_language": "",
   "target_language": "",
   "translated_text": "Zuberman Joel Isaac, his wife Hana. Zuberman Jacob, his wife Sarah, their son Isaac. Zuberman Moshe, his wife Yochabed, the children: Aaron, Rebecca, Haya. Zuberman Shmuel and his son Haim Muni. Zuberman Bayle, her son Moshe. .\n"
  },
  {
   "upper_left_point": {
    "x": 154,
    "y": 500
   },
   "bottom_right_point": {
    "x": 423,
    "y": 523
   },
   "text": "זובערמאן הענען , זיין פרוי חנה און די קינדער : דוד און יעקב . זיסבערג יהושע , זיין פרוי פייגע און צוויי קינדער . ",
   "origin_language": "",
   "target_language": "",
   "translated_text": "Zuberman, his wife Hannah and their children: David and Jacob. Zisberg Joshua, his wife Fige and two children. .\n"
  },
  {
   "upper_left_point": {
    "x": 207,
    "y": 523
   },
   "bottom_right_point": {
    "x": 424,
    "y": 572
   },
   "text": "זייף זעליק . זיסבערג שלמה , זיין פרוי מירל . זיידל אברהם , זיין פרוי רייזל , די טאכטער בריינע . ",
   "origin_language": "",
   "target_language": "",
   "translated_text": "So be it. Zisberg Shlomo, his wife Mirl. Zeidal Avraham, his wife Reizel, their daughter Breina. .\n"
  },
  {
   "upper_left_point": {
    "x": 242,
    "y": 574
   },
   "bottom_right_point": {
    "x": 423,
    "y": 610
   },
   "text": "זייף אברהם אהרן . זייף יוסף , זיין פרוי חיה און צוויי קינדער . זילבערבערג משה מיכאל , זיין פרוי נעכע . ",
   "origin_language": "",
   "target_language": "",
   "translated_text": "Soap Avraham Aharon. Joseph Joseph, his wife Haya and two children. Zilberberg Moshe Michael, his wife Neche. .\n"
  }
 ],
 "filename": "tmp/horodlo/56990876.jpg",
 "order": 312,
 "page_number": "310"
}